remarshal/__init__.py
remarshal/__main__.py
remarshal/main.py
remarshal/py.typed
remarshal-1.3.0.dist-info/METADATA
remarshal-1.3.0.dist-info/WHEEL
remarshal-1.3.0.dist-info/entry_points.txt
remarshal-1.3.0.dist-info/licenses/LICENSE
remarshal-1.3.0.dist-info/RECORD
