Metadata-Version: 2.4
Name: remarshal
Version: 1.3.0
Summary: Convert between CBOR, JSON, MessagePack, TOML, and YAML
License: MIT
License-File: LICENSE
Keywords: converter,cbor,json,messagepack,msgpack,toml,yaml
Author: D. Bohdan
Author-email: dbohdan@dbohdan.com
Requires-Python: >=3.10
Classifier: Development Status :: 5 - Production/Stable
Classifier: Environment :: Console
Classifier: License :: OSI Approved :: MIT License
Classifier: Operating System :: MacOS :: MacOS X
Classifier: Operating System :: Microsoft :: Windows
Classifier: Operating System :: POSIX
Classifier: Programming Language :: Python :: 3
Classifier: Topic :: File Formats
Classifier: Topic :: File Formats :: JSON
Classifier: Topic :: Utilities
Provides-Extra: dev
Requires-Dist: cbor2 (>=5.8,<6.0)
Requires-Dist: codespell[toml] (>=2.2.5,<3.0) ; extra == "dev"
Requires-Dist: colorama (>=0.4.6,<0.5)
Requires-Dist: pyright (==1.1.399) ; extra == "dev"
Requires-Dist: pytest (>=8.0,<9.0) ; extra == "dev"
Requires-Dist: pytest-cov (>=4.1,<5.0) ; extra == "dev"
Requires-Dist: rich-argparse (>=1.7.2,<2.0)
Requires-Dist: ruamel.yaml (>=0.19,<0.20)
Requires-Dist: ruff (==0.11.5) ; extra == "dev"
Requires-Dist: snoop (>=0.6,<0.7) ; extra == "dev"
Requires-Dist: tomli (>=2.4,<3.0)
Requires-Dist: tomlkit (>=0.14,<0.15)
Requires-Dist: types-python-dateutil (>=2.8.19.13,<3.0) ; extra == "dev"
Requires-Dist: u-msgpack-python (>=2.8,<3.0)
Project-URL: Repository, https://github.com/remarshal-project/remarshal
